sql_dependency_manager-0.1.1.dist-info/licenses/LICENSE
sqlblocks/__init__.py
sql_dependency_manager-0.1.1.dist-info/METADATA
sql_dependency_manager-0.1.1.dist-info/WHEEL
sql_dependency_manager-0.1.1.dist-info/top_level.txt
sql_dependency_manager-0.1.1.dist-info/RECORD
