Metadata-Version: 2.4
Name: sql-dependency-manager
Version: 0.1.1
Summary: SQL query assembler with dependency resolution for reusable code blocks
Author-email: picodart <ya-artem@inbox.ru>
License: MIT
Project-URL: Homepage, https://github.com/picodart/SQLBlocks
Project-URL: Repository, https://github.com/picodart/SQLBlocks
Keywords: sql,cte,query-builder,database,code-reuse,sql-composer
Classifier: Development Status :: 3 - Alpha
Classifier: Intended Audience :: Developers
Classifier: License :: OSI Approved :: MIT License
Classifier: Programming Language :: Python :: 3
Classifier: Programming Language :: Python :: 3.8
Classifier: Programming Language :: Python :: 3.9
Classifier: Programming Language :: Python :: 3.10
Classifier: Programming Language :: Python :: 3.11
Classifier: Programming Language :: Python :: 3.12
Classifier: Topic :: Database
Classifier: Topic :: Software Development :: Libraries :: Python Modules
License-File: LICENSE
Dynamic: license-file
